hwpx/__init__.py
hwpx/document.py
hwpx/package.py
hwpx/templates.py
hwpx/data/Skeleton.hwpx
hwpx/opc/package.py
hwpx/oxml/__init__.py
hwpx/oxml/body.py
hwpx/oxml/common.py
hwpx/oxml/document.py
hwpx/oxml/header.py
hwpx/oxml/parser.py
hwpx/oxml/schema.py
hwpx/oxml/utils.py
hwpx/tools/__init__.py
hwpx/tools/object_finder.py
hwpx/tools/text_extractor.py
hwpx/tools/validator.py
hwpx/tools/_schemas/header.xsd
hwpx/tools/_schemas/section.xsd
python_hwpx-1.9.dist-info/licenses/LICENSE
python_hwpx-1.9.dist-info/METADATA
python_hwpx-1.9.dist-info/WHEEL
python_hwpx-1.9.dist-info/entry_points.txt
python_hwpx-1.9.dist-info/top_level.txt
python_hwpx-1.9.dist-info/RECORD
