Metadata-Version: 2.4
Name: python-hwpx
Version: 1.9
Summary: Hancom HWPX 패키지를 로드하고 편집하기 위한 Python 유틸리티 모음
Author: python-hwpx Maintainers
License: Non-Commercial License
Project-URL: Homepage, https://github.com/airmang/python-hwpx
Project-URL: Documentation, https://github.com/airmang/python-hwpx/tree/main/docs
Project-URL: Issues, https://github.com/airmang/python-hwpx/issues
Keywords: hwp,hwpx,hancom,opc,xml
Classifier: Development Status :: 3 - Alpha
Classifier: Intended Audience :: Developers
Classifier: License :: OSI Approved :: MIT License
Classifier: Programming Language :: Python :: 3
Classifier: Programming Language :: Python :: 3.10
Classifier: Programming Language :: Python :: 3.11
Classifier: Programming Language :: Python :: 3.12
Classifier: Topic :: Software Development :: Libraries
Classifier: Topic :: Text Processing :: Markup :: XML
Requires-Python: >=3.10
License-File: LICENSE
Requires-Dist: lxml<6,>=4.9
Provides-Extra: dev
Requires-Dist: build>=1.0; extra == "dev"
Requires-Dist: twine>=4.0; extra == "dev"
Requires-Dist: pytest>=7.4; extra == "dev"
Provides-Extra: test
Requires-Dist: pytest>=7.4; extra == "test"
Dynamic: license-file
